setup.py
beadalize/__init__.py
beadalize/__version__.py
beadalize.egg-info/PKG-INFO
beadalize.egg-info/SOURCES.txt
beadalize.egg-info/dependency_links.txt
beadalize.egg-info/requires.txt
beadalize.egg-info/top_level.txt