Metadata-Version: 1.1
Name: beadalize
Version: 0.0.1
Summary: A package to create ironing bead patterns from images
Home-page: https://github.com/BrechtBa/beadalize
Author: Brecht Baeten
Author-email: brecht.baeten@gmail.com
License: GPLv3
Platform: UNKNOWN
Classifier: Programming Language :: Python :: 3.6
